mocktalk/__init__.py
mocktalk/__main__.py
mocktalk/cli.py
mocktalk/script.py
mocktalk/servers.py
mocktalk/ssh.py
mocktalk/telnet.py
mocktalk-0.0.3.dist-info/LICENSE
mocktalk-0.0.3.dist-info/METADATA
mocktalk-0.0.3.dist-info/WHEEL
mocktalk-0.0.3.dist-info/entry_points.txt
mocktalk-0.0.3.dist-info/top_level.txt
mocktalk-0.0.3.dist-info/RECORD
