Metadata-Version: 2.1
Name: mocktalk
Version: 0.0.3
Summary: Mock telnet and ssh connections in Python
Home-page: https://github.com/boryszef/mocktalk
License: MIT
License-File: LICENSE
Requires-Dist: paramiko
Requires-Dist: click
